nutshell/__init__.py
nutshell/entities.py
nutshell/methods.py
nutshell/nutshell_api.py
nutshell/responses.py
nutshell-0.4.4.dist-info/METADATA
nutshell-0.4.4.dist-info/WHEEL
nutshell-0.4.4.dist-info/RECORD
