Metadata-Version: 2.1
Name: nutshell
Version: 0.4.4
Summary: Python wrapper on the Nutshell CRM JSON RPC API
Home-page: https://github.com/biguscj7/nutshell.git
License: "MIT"
Author: Mark Nyberg
Author-email: bigusdeveloper@gmail.com
Requires-Python: >=3.11,<4.0
Classifier: License :: OSI Approved :: MIT License
Classifier: License :: Other/Proprietary License
Classifier: Operating System :: OS Independent
Classifier: Programming Language :: Python :: 3
Classifier: Programming Language :: Python :: 3.11
Classifier: Programming Language :: Python :: 3.12
Requires-Dist: aiohttp (>=3.9.3,<4.0.0)
Requires-Dist: coverage (>=7.5.4,<8.0.0)
Requires-Dist: pydantic (>=2.6.4,<3.0.0)
Project-URL: Repository, https://github.com/biguscj7/nutshell.git
